muirc.py
setup.py
muirc.egg-info/PKG-INFO
muirc.egg-info/SOURCES.txt
muirc.egg-info/dependency_links.txt
muirc.egg-info/top_level.txt