Metadata-Version: 1.0
Name: muirc
Version: 1.0
Summary: Micro IRC client
Home-page: https://github.com/Gawen/muirc
Author: Gawen Arab
Author-email: g@wenarab.com
License: MIT
Platform: UNKNOWN
Classifier: Development Status :: 5 - Production/Stable
Classifier: License :: OSI Approved :: MIT License
Classifier: Operating System :: OS Independent
Classifier: Programming Language :: Python
Classifier: Topic :: Communications :: Chat
Classifier: Topic :: Internet
Classifier: Topic :: Software Development :: Libraries :: Python Modules
